changeloggh/__init__.py
changeloggh/__main__.py
changeloggh/changelog.py
changeloggh/cli.py
changeloggh/url_utils.py
changeloggh/version_utils.py
changeloggh-1.2.1.dist-info/METADATA
changeloggh-1.2.1.dist-info/WHEEL
changeloggh-1.2.1.dist-info/entry_points.txt
changeloggh-1.2.1.dist-info/licenses/LICENSE
changeloggh-1.2.1.dist-info/RECORD
