Metadata-Version: 2.4
Name: changeloggh
Version: 1.2.1
Summary: changeloggh is a command line tool that generates changelog files for github
License: MIT
License-File: LICENSE
Keywords: changelog,changeloggh
Author: Saúl Piña
Author-email: sauljabin@gmail.com
Requires-Python: >=3.10,<3.15
Classifier: License :: OSI Approved :: MIT License
Classifier: Environment :: Console
Classifier: Operating System :: MacOS
Classifier: Operating System :: Unix
Classifier: Programming Language :: Python :: 3.10
Classifier: Programming Language :: Python :: 3.11
Classifier: Programming Language :: Python :: 3.12
Classifier: Programming Language :: Python :: 3.13
Classifier: Programming Language :: Python :: 3.14
Requires-Dist: cloup (>=3)
Requires-Dist: jinja2 (>=3)
Requires-Dist: rich (>=14)
Requires-Dist: semver (>=3)
Requires-Dist: textual (>=6)
Project-URL: Homepage, https://github.com/sauljabin/changeloggh
Project-URL: Repository, https://github.com/sauljabin/changeloggh
